Autogasuptake/Autogasuptake.py
Autogasuptake/__init__.py
Autogasuptake/__main__.py
Autogasuptake-1.2.9.dist-info/METADATA
Autogasuptake-1.2.9.dist-info/WHEEL
Autogasuptake-1.2.9.dist-info/entry_points.txt
Autogasuptake-1.2.9.dist-info/top_level.txt
Autogasuptake-1.2.9.dist-info/RECORD
